PointBlaster/.DS_Store
PointBlaster/PointBlaster.py
PointBlaster/__init__.py
PointBlaster/db/.DS_Store
PointBlaster/db/point_mutation/.DS_Store
PointBlaster/db/point_mutation/campylobacter/.DS_Store
PointBlaster/db/point_mutation/campylobacter/23S.fsa
PointBlaster/db/point_mutation/campylobacter/RNA_genes.txt
PointBlaster/db/point_mutation/campylobacter/campylobacter.comp.b
PointBlaster/db/point_mutation/campylobacter/campylobacter.fsa
PointBlaster/db/point_mutation/campylobacter/campylobacter.fsa.original
PointBlaster/db/point_mutation/campylobacter/campylobacter.length.b
PointBlaster/db/point_mutation/campylobacter/campylobacter.name
PointBlaster/db/point_mutation/campylobacter/campylobacter.seq.b
PointBlaster/db/point_mutation/campylobacter/genes.txt
PointBlaster/db/point_mutation/campylobacter/gyrA.fsa
PointBlaster/db/point_mutation/campylobacter/gyrA_2.fsa
PointBlaster/db/point_mutation/campylobacter/phenotypes.txt
PointBlaster/db/point_mutation/campylobacter/resistens-overview.txt
PointBlaster/db/point_mutation/campylobacter/rpsL.fsa
PointBlaster/db/point_mutation/salmonella/16S-rrsD.fsa
PointBlaster/db/point_mutation/salmonella/RNA_genes.txt
PointBlaster/db/point_mutation/salmonella/acrB.fsa
PointBlaster/db/point_mutation/salmonella/genes.txt
PointBlaster/db/point_mutation/salmonella/gyrA.fsa
PointBlaster/db/point_mutation/salmonella/gyrB.fsa
PointBlaster/db/point_mutation/salmonella/parC.fsa
PointBlaster/db/point_mutation/salmonella/parE.fsa
PointBlaster/db/point_mutation/salmonella/phenotypes.txt
PointBlaster/db/point_mutation/salmonella/pmrA.fsa
PointBlaster/db/point_mutation/salmonella/pmrB.fsa
PointBlaster/db/point_mutation/salmonella/resistens-overview.txt
PointBlaster/db/point_mutation/salmonella/salmonella.comp.b
PointBlaster/db/point_mutation/salmonella/salmonella.fsa
PointBlaster/db/point_mutation/salmonella/salmonella.fsa.original
PointBlaster/db/point_mutation/salmonella/salmonella.length.b
PointBlaster-0.2.6.dist-info/METADATA
PointBlaster-0.2.6.dist-info/WHEEL
PointBlaster-0.2.6.dist-info/entry_points.txt
PointBlaster-0.2.6.dist-info/top_level.txt
PointBlaster-0.2.6.dist-info/RECORD
