Metadata-Version: 2.1
Name: PointBlaster
Version: 0.2.6
Summary: find point mutation in assembled genomes
Home-page: https://github.com/hbucqp/PointBlaster
Author: Qingpo Cui
Author-email: cqp@cau.edu.cn
License: MIT Licence
Keywords: pip,wgs,blastn,pointmutation
Platform: any
Classifier: Development Status :: 4 - Beta
Classifier: Intended Audience :: Developers
Classifier: Topic :: Software Development :: Build Tools
Classifier: License :: OSI Approved :: MIT License
Classifier: Programming Language :: Python :: 3.9
Requires-Dist: Bio
Requires-Dist: pandas
Requires-Dist: numpy
Requires-Dist: cvmblaster (>=0.4.5)
Requires-Dist: setuptools
